{
  "gitSyncId": "66f5118e8bc3331e3fb1ae0a_3fddc2c2-ef9b-4360-a92d-7ea49f3bedcd",
  "id": "Waiting Page 1_JSObject1.myFun1",
  "pluginId": "js-plugin",
  "pluginType": "JS",
  "unpublishedAction": {
    "actionConfiguration": {
      "encodeParamsToggle": true,
      "jsArguments": [],
      "paginationType": "NONE",
      "timeoutInMillisecond": 10000
    },
    "clientSideExecution": true,
    "collectionId": "Waiting Page 1_JSObject1",
    "confirmBeforeExecute": false,
    "datasource": {
      "isAutoGenerated": false,
      "name": "UNUSED_DATASOURCE",
      "pluginId": "js-plugin"
    },
    "dynamicBindingPathList": [
      {
        "key": "body"
      }
    ],
    "executeOnLoad": false,
    "fullyQualifiedName": "JSObject1.myFun1",
    "name": "myFun1",
    "pageId": "Waiting Page 1",
    "userSetOnLoad": false
  }
}